teaching_optimization/__init__.py
teaching_optimization/linear_optimization.py
teaching_optimization/matrices.py
teaching_optimization/plot_function.py
teaching_optimization/simplex.py
teaching_optimization/simplex_tableau.py
teaching_optimization/simplex_tableau_phase_two.py
teaching_optimization/tableau.py
teaching_optimization/to_jupyter.py
teaching_optimization/variables.py
teaching_optimization/branch_and_bound/__init__.py
teaching_optimization/branch_and_bound/branch_and_bound_milp.py
teaching_optimization/branch_and_bound/solution.py
teaching_optimization/branch_and_bound/subproblem.py
teaching_optimization/linear_constraints/__init__.py
teaching_optimization/linear_constraints/constraint.py
teaching_optimization/linear_constraints/draw_polyhedron.py
teaching_optimization/linear_constraints/linear_constraints.py
teaching_optimization/linear_constraints/polyhedron_2d.py
teaching_optimization/linear_constraints/standard_canonical.py
teaching_optimization/linear_constraints/standard_form.py
teaching_optimization/linear_constraints/variable.py
teaching_optimization/linear_constraints/networks/__init__.py
teaching_optimization/linear_constraints/networks/draw_network.py
teaching_optimization/networks/__init__.py
teaching_optimization/networks/bellman.py
teaching_optimization/networks/draw_network.py
teaching_optimization/networks/shortest_path_algorithm.py
teaching_optimization-0.0.2.dist-info/METADATA
teaching_optimization-0.0.2.dist-info/WHEEL
teaching_optimization-0.0.2.dist-info/top_level.txt
teaching_optimization-0.0.2.dist-info/RECORD
